pgframe/__init__.py
pgframe/pgframe.py
pgframe-0.1.0.dist-info/METADATA
pgframe-0.1.0.dist-info/WHEEL
pgframe-0.1.0.dist-info/licenses/LICENSE
pgframe-0.1.0.dist-info/RECORD
