Metadata-Version: 2.4
Name: pgframe
Version: 0.1.0
Summary: A Python bridge between PostgreSQL and DataFrame libraries.
Project-URL: Homepage, https://github.com/randomseed42/pgframe
Author-email: randomseed42 <randomseed42@protonmail.com>
Maintainer-email: randomseed42 <randomseed42@protonmail.com>
License:                                  Apache License
License-File: LICENSE
Keywords: dataframe,postgresql,sql
Classifier: Development Status :: 3 - Alpha
Classifier: Intended Audience :: Developers
Classifier: License :: OSI Approved :: MIT License
Classifier: Programming Language :: Python :: 3.11
Classifier: Topic :: Database
Classifier: Topic :: Software Development :: Libraries
Requires-Python: >=3.11
Requires-Dist: alembic
Requires-Dist: pandas
Requires-Dist: psycopg[binary]
Requires-Dist: sqlalchemy
